LICENSE.txt
MANIFEST.in
README.rst
setup.cfg
setup.py
pyjc/__init__.py
pyjc/helloworld.py
pyjc.egg-info/PKG-INFO
pyjc.egg-info/SOURCES.txt
pyjc.egg-info/dependency_links.txt
pyjc.egg-info/top_level.txt