Metadata-Version: 1.2
Name: pyjc
Version: 0.1.2
Summary: An educational deep learning framework
Home-page: http://github.com/Atlas7/pyjc
Author: Johnny Chan
Author-email: johnnychan0302@gmail.com
License: MIT
Download-URL: https://github.com/Atlas7/pyjc/archive/v0.1.2.tar.gz
Keywords: deep learning,education,scientific computing,artificial intelligence
Platform: UNKNOWN
Classifier: Development Status :: 3 - Alpha
Classifier: Intended Audience :: Developers
Classifier: Topic :: Scientific/Engineering :: Artificial Intelligence
Classifier: Natural Language :: English
Classifier: Operating System :: OS Independent
Classifier: License :: OSI Approved :: MIT License
Classifier: Programming Language :: Python :: 3.6
Requires-Python: ==3.6.*
